ptz_control_lib/__init__.py
ptz_control_lib/protocols.py
ptz_control_lib/ptz_controller.py
pyptzcontroller-0.1.2.dist-info/licenses/LICENSE
pyptzcontroller-0.1.2.dist-info/METADATA
pyptzcontroller-0.1.2.dist-info/WHEEL
pyptzcontroller-0.1.2.dist-info/top_level.txt
pyptzcontroller-0.1.2.dist-info/RECORD
