Metadata-Version: 2.4
Name: pyptzcontroller
Version: 0.1.2
Summary: 一个简单易用的 Pelco-D 协议云台控制库
Author-email: yuyu <jin2686641273@gmail.com>
License: MIT License
Keywords: ptz,pelco-d,serial control,camera control,rs485
Classifier: Development Status :: 4 - Beta
Classifier: Intended Audience :: Developers
Classifier: License :: OSI Approved :: MIT License
Classifier: Operating System :: OS Independent
Classifier: Programming Language :: Python :: 3
Classifier: Topic :: System :: Hardware
Requires-Python: >=3.7
License-File: LICENSE
Requires-Dist: pyserial
Dynamic: license-file
